<?xml version="1.0" encoding="utf-8"?>
<MetaDataVaultImplementation>
  <BusinessLinkSatelliteImplementationList>
    <BusinessLinkSatelliteImplementation Id="default-business-link-satellite">
      <TableNamePattern>BLS_{ParentName}_{Name}</TableNamePattern>
      <ParentHashKeyColumnName>LinkHashKey</ParentHashKeyColumnName>
      <ParentHashKeyDataType>binary(16)</ParentHashKeyDataType>
      <HashDiffColumnName>HashDiff</HashDiffColumnName>
      <HashDiffDataType>binary(16)</HashDiffDataType>
      <LoadTimestampColumnName>LoadTimestamp</LoadTimestampColumnName>
      <LoadTimestampDataType>datetime2(7)</LoadTimestampDataType>
      <RecordSourceColumnName>RecordSource</RecordSourceColumnName>
      <RecordSourceDataType>nvarchar(256)</RecordSourceDataType>
    </BusinessLinkSatelliteImplementation>
  </BusinessLinkSatelliteImplementationList>
</MetaDataVaultImplementation>
