<?xml version="1.0" encoding="utf-8"?>
<MetaSqlDeployManifest xmlns:xsi="http://www.w3.org/2001/XMLSchema-instance" xmlns:xsd="http://www.w3.org/2001/XMLSchema">
  <DeployManifestList>
    <DeployManifest Id="DeployManifest:1">
      <CreatedUtc>2026-03-27T22:07:52.5654973Z</CreatedUtc>
      <ExpectedLiveDatabasePresence>Missing</ExpectedLiveDatabasePresence>
      <LiveInstanceFingerprint>da3774c744674470b881b3288fc0e1e25df0065bc80c190727b534f9bafa7e3c</LiveInstanceFingerprint>
      <Name>DeployManifest</Name>
      <SourceInstanceFingerprint>29b9214bcc572ddc6231dc7942289fd39bb0e10b9b961202d1276f8b65a1fbb2</SourceInstanceFingerprint>
      <TargetDescription>Scope=(all)</TargetDescription>
    </DeployManifest>
  </DeployManifestList>
</MetaSqlDeployManifest>